geoparser/__init__.py
geoparser/__main__.py
geoparser/annotator/README.md
geoparser/annotator/__init__.py
geoparser/annotator/app.py
geoparser/annotator/constants.py
geoparser/annotator/db/crud/__init__.py
geoparser/annotator/db/crud/base.py
geoparser/annotator/db/crud/document.py
geoparser/annotator/db/crud/session.py
geoparser/annotator/db/crud/settings.py
geoparser/annotator/db/crud/toponym.py
geoparser/annotator/db/db.py
geoparser/annotator/db/models/__init__.py
geoparser/annotator/db/models/document.py
geoparser/annotator/db/models/session.py
geoparser/annotator/db/models/settings.py
geoparser/annotator/db/models/toponym.py
geoparser/annotator/db/models/validators.py
geoparser/annotator/dependencies.py
geoparser/annotator/exceptions.py
geoparser/annotator/metadata.py
geoparser/annotator/models/api.py
geoparser/annotator/static/annotate.css
geoparser/annotator/static/annotate.js
geoparser/annotator/static/continue_session.js
geoparser/annotator/templates/html/annotate.html
geoparser/annotator/templates/html/continue_session.html
geoparser/annotator/templates/html/index.html
geoparser/annotator/templates/html/start_new_session.html
geoparser/annotator/templates/js/url_base.js
geoparser/cli/__init__.py
geoparser/cli/annotator.py
geoparser/cli/app.py
geoparser/cli/download.py
geoparser/context/__init__.py
geoparser/context/context.py
geoparser/db/crud/__init__.py
geoparser/db/crud/base.py
geoparser/db/crud/context.py
geoparser/db/crud/document.py
geoparser/db/crud/feature.py
geoparser/db/crud/gazetteer.py
geoparser/db/crud/name.py
geoparser/db/crud/project.py
geoparser/db/crud/recognition.py
geoparser/db/crud/recognizer.py
geoparser/db/crud/reference.py
geoparser/db/crud/referent.py
geoparser/db/crud/resolution.py
geoparser/db/crud/resolver.py
geoparser/db/crud/source.py
geoparser/db/db.py
geoparser/db/extensions/spatialite/LICENSE
geoparser/db/extensions/spatialite/binaries/darwin-arm64/.gitkeep
geoparser-0.3.0.dist-info/METADATA
geoparser-0.3.0.dist-info/WHEEL
geoparser-0.3.0.dist-info/licenses/LICENSE
geoparser-0.3.0.dist-info/RECORD
