Metadata-Version: 2.4
Name: geoparser
Version: 0.3.0
Summary: A customizable geoparsing library for unstructured text
License: MIT
License-File: LICENSE
Author: Diego Gomes
Author-email: diego.gomes@uzh.ch
Requires-Python: >=3.10,<3.14
Classifier: License :: OSI Approved :: MIT License
Classifier: Programming Language :: Python :: 3
Classifier: Programming Language :: Python :: 3.10
Classifier: Programming Language :: Python :: 3.11
Classifier: Programming Language :: Python :: 3.12
Classifier: Programming Language :: Python :: 3.13
Requires-Dist: accelerate (>=1.11.0,<2.0.0)
Requires-Dist: appdirs (>=1.4.4,<2.0.0)
Requires-Dist: datasets (>=4.3.0,<5.0.0)
Requires-Dist: fastapi (>=0.121.0,<0.122.0)
Requires-Dist: geopandas (>=1.1.1,<2.0.0)
Requires-Dist: markupsafe (>=3.0.3,<4.0.0)
Requires-Dist: pandas (>=2.3.3,<3.0.0)
Requires-Dist: pydantic (>=2.12.3,<3.0.0)
Requires-Dist: pyogrio (>=0.11.1,<0.12.0)
Requires-Dist: pyproj (>=3.7.1,<4.0.0)
Requires-Dist: python-multipart (>=0.0.20,<0.0.21)
Requires-Dist: pyyaml (>=6.0.3,<7.0.0)
Requires-Dist: requests (>=2.32.5,<3.0.0)
Requires-Dist: sentence-transformers (>=5.1.2,<6.0.0)
Requires-Dist: shapely (>=2.1.2,<3.0.0)
Requires-Dist: spacy (>=3.8.7,<4.0.0)
Requires-Dist: sqlalchemy (>=2.0.44,<3.0.0)
Requires-Dist: sqlmodel (>=0.0.27,<0.0.28)
Requires-Dist: torch (>=2.9.0,<3.0.0)
Requires-Dist: tqdm (>=4.67.1,<5.0.0)
Requires-Dist: transformers (>=4.57.1,<5.0.0)
Requires-Dist: typer (>=0.20.0,<0.21.0)
Requires-Dist: uvicorn (>=0.38.0,<0.39.0)
Requires-Dist: werkzeug (>=3.1.3,<4.0.0)
Project-URL: Homepage, https://geoparser.app
Project-URL: Repository, https://github.com/dguzh/geoparser
